Metadata-Version: 2.4
Name: morphodeep
Version: 0.0.1
Summary: Instance segmentation of membranes
Author: Emmanuel Faure
Author-email: emmanuel.faure@lirmm.fr
License: 
Keywords: image analysis,bioimage,segmentation,instance-segmentation,deep learning,unet,napari plugin,microscopy
Classifier: Development Status :: 2 - Pre-Alpha
Classifier: Framework :: napari
Classifier: Intended Audience :: Developers
Classifier: License :: OSI Approved :: GNU Lesser General Public License v3 (LGPLv3)
Classifier: Operating System :: OS Independent
Classifier: Programming Language :: Python
Classifier: Programming Language :: Python :: 3
Classifier: Programming Language :: Python :: 3 :: Only
Classifier: Programming Language :: Python :: 3.10
Classifier: Programming Language :: Python :: 3.11
Classifier: Programming Language :: Python :: 3.12
Classifier: Programming Language :: Python :: 3.13
Classifier: Topic :: Scientific/Engineering :: Image Processing
Requires-Python: >=3.10
License-File: LICENSE
Requires-Dist: numpy
Requires-Dist: tqdm
Requires-Dist: tensorflow
Requires-Dist: scikit-image
Requires-Dist: matplotlib
Requires-Dist: nibabel
Requires-Dist: scipy
Requires-Dist: h5py
Requires-Dist: paramiko
Requires-Dist: scp
Requires-Dist: pandas
Provides-Extra: napari
Requires-Dist: napari>=0.4.19; extra == "napari"
Requires-Dist: magicgui>=0.6.0; extra == "napari"
Requires-Dist: PyQt5; extra == "napari"
Requires-Dist: qtpy>=2.0.0; extra == "napari"
Dynamic: license-file
